{"conclusion":"failure","createdAt":"2026-04-29T18:04:44Z","databaseId":25125551441,"event":"push","headBranch":"main","headSha":"c7626c0d9d2a08907634ebd5babcaa7579b83222","jobs":[{"completedAt":"2026-04-29T18:04:53Z","conclusion":"failure","databaseId":73637479652,"name":"Apply Changesets","startedAt":"2026-04-29T18:04:47Z","status":"completed","steps":[{"completedAt":"2026-04-29T18:04:49Z","conclusion":"success","name":"Set up job","number":1,"startedAt":"2026-04-29T18:04:48Z","status":"completed"},{"completedAt":"2026-04-29T18:04:51Z","conclusion":"success","name":"Run actions/checkout@v4","number":2,"startedAt":"2026-04-29T18:04:49Z","status":"completed"},{"completedAt":"2026-04-29T18:04:51Z","conclusion":"success","name":"Check for changesets","number":3,"startedAt":"2026-04-29T18:04:51Z","status":"completed"},{"completedAt":"2026-04-29T18:04:51Z","conclusion":"failure","name":"Apply changesets","number":4,"startedAt":"2026-04-29T18:04:51Z","status":"completed"},{"completedAt":"2026-04-29T18:04:51Z","conclusion":"success","name":"Post Run actions/checkout@v4","number":8,"startedAt":"2026-04-29T18:04:51Z","status":"completed"},{"completedAt":"2026-04-29T18:04:51Z","conclusion":"success","name":"Complete job","number":9,"startedAt":"2026-04-29T18:04:51Z","status":"completed"}],"url":"https://github.com/link-foundation/box/actions/runs/25125551441/job/73637479652"},{"completedAt":"2026-04-29T18:04:45Z","conclusion":"skipped","databaseId":73637479940,"name":"Check for Manual Version Changes","startedAt":"2026-04-29T18:04:45Z","status":"completed","steps":[],"url":"https://github.com/link-foundation/box/actions/runs/25125551441/job/73637479940"},{"completedAt":"2026-04-29T18:04:45Z","conclusion":"skipped","databaseId":73637479967,"name":"version-bump","startedAt":"2026-04-29T18:04:45Z","status":"completed","steps":[],"url":"https://github.com/link-foundation/box/actions/runs/25125551441/job/73637479967"},{"completedAt":"2026-04-29T18:04:45Z","conclusion":"skipped","databaseId":73637480050,"name":"Check for Changesets","startedAt":"2026-04-29T18:04:45Z","status":"completed","steps":[],"url":"https://github.com/link-foundation/box/actions/runs/25125551441/job/73637480050"},{"completedAt":"2026-04-29T18:04:54Z","conclusion":"skipped","databaseId":73637505117,"name":"pr-test / js","startedAt":"2026-04-29T18:04:54Z","status":"completed","steps":[],"url":"https://github.com/link-foundation/box/actions/runs/25125551441/job/73637505117"},{"completedAt":"2026-04-29T18:04:54Z","conclusion":"skipped","databaseId":73637505128,"name":"detect-changes","startedAt":"2026-04-29T18:04:54Z","status":"completed","steps":[],"url":"https://github.com/link-foundation/box/actions/runs/25125551441/job/73637505128"},{"completedAt":"2026-04-29T18:04:54Z","conclusion":"skipped","databaseId":73637505157,"name":"build-js-arm64","startedAt":"2026-04-29T18:04:54Z","status":"completed","steps":[],"url":"https://github.com/link-foundation/box/actions/runs/25125551441/job/73637505157"},{"completedAt":"2026-04-29T18:04:54Z","conclusion":"skipped","databaseId":73637505178,"name":"build-js-amd64","startedAt":"2026-04-29T18:04:54Z","status":"completed","steps":[],"url":"https://github.com/link-foundation/box/actions/runs/25125551441/job/73637505178"},{"completedAt":"2026-04-29T18:04:54Z","conclusion":"skipped","databaseId":73637505300,"name":"build-essentials-amd64","startedAt":"2026-04-29T18:04:54Z","status":"completed","steps":[],"url":"https://github.com/link-foundation/box/actions/runs/25125551441/job/73637505300"},{"completedAt":"2026-04-29T18:04:54Z","conclusion":"skipped","databaseId":73637505393,"name":"js-manifest","startedAt":"2026-04-29T18:04:54Z","status":"completed","steps":[],"url":"https://github.com/link-foundation/box/actions/runs/25125551441/job/73637505393"},{"completedAt":"2026-04-29T18:04:54Z","conclusion":"skipped","databaseId":73637505666,"name":"pr-test / ${{ matrix.language }}","startedAt":"2026-04-29T18:04:54Z","status":"completed","steps":[],"url":"https://github.com/link-foundation/box/actions/runs/25125551441/job/73637505666"},{"completedAt":"2026-04-29T18:04:54Z","conclusion":"skipped","databaseId":73637505668,"name":"build-languages-arm64","startedAt":"2026-04-29T18:04:54Z","status":"completed","steps":[],"url":"https://github.com/link-foundation/box/actions/runs/25125551441/job/73637505668"},{"completedAt":"2026-04-29T18:04:54Z","conclusion":"skipped","databaseId":73637505690,"name":"essentials-manifest","startedAt":"2026-04-29T18:04:54Z","status":"completed","steps":[],"url":"https://github.com/link-foundation/box/actions/runs/25125551441/job/73637505690"},{"completedAt":"2026-04-29T18:04:54Z","conclusion":"skipped","databaseId":73637505703,"name":"pr-test / essentials","startedAt":"2026-04-29T18:04:54Z","status":"completed","steps":[],"url":"https://github.com/link-foundation/box/actions/runs/25125551441/job/73637505703"},{"completedAt":"2026-04-29T18:04:54Z","conclusion":"skipped","databaseId":73637505723,"name":"build-essentials-arm64","startedAt":"2026-04-29T18:04:54Z","status":"completed","steps":[],"url":"https://github.com/link-foundation/box/actions/runs/25125551441/job/73637505723"},{"completedAt":"2026-04-29T18:04:54Z","conclusion":"skipped","databaseId":73637506017,"name":"build-languages-amd64","startedAt":"2026-04-29T18:04:54Z","status":"completed","steps":[],"url":"https://github.com/link-foundation/box/actions/runs/25125551441/job/73637506017"},{"completedAt":"2026-04-29T18:04:54Z","conclusion":"skipped","databaseId":73637506048,"name":"pr-test / dind-${{ matrix.variant }}","startedAt":"2026-04-29T18:04:54Z","status":"completed","steps":[],"url":"https://github.com/link-foundation/box/actions/runs/25125551441/job/73637506048"},{"completedAt":"2026-04-29T18:04:54Z","conclusion":"skipped","databaseId":73637506207,"name":"languages-manifest","startedAt":"2026-04-29T18:04:54Z","status":"completed","steps":[],"url":"https://github.com/link-foundation/box/actions/runs/25125551441/job/73637506207"},{"completedAt":"2026-04-29T18:04:54Z","conclusion":"skipped","databaseId":73637506386,"name":"pr-test / full","startedAt":"2026-04-29T18:04:54Z","status":"completed","steps":[],"url":"https://github.com/link-foundation/box/actions/runs/25125551441/job/73637506386"},{"completedAt":"2026-04-29T18:04:54Z","conclusion":"skipped","databaseId":73637506394,"name":"docker-build-push","startedAt":"2026-04-29T18:04:54Z","status":"completed","steps":[],"url":"https://github.com/link-foundation/box/actions/runs/25125551441/job/73637506394"},{"completedAt":"2026-04-29T18:04:54Z","conclusion":"skipped","databaseId":73637506402,"name":"docker-build-test","startedAt":"2026-04-29T18:04:54Z","status":"completed","steps":[],"url":"https://github.com/link-foundation/box/actions/runs/25125551441/job/73637506402"},{"completedAt":"2026-04-29T18:04:54Z","conclusion":"skipped","databaseId":73637506513,"name":"docker-build-push-arm64","startedAt":"2026-04-29T18:04:54Z","status":"completed","steps":[],"url":"https://github.com/link-foundation/box/actions/runs/25125551441/job/73637506513"},{"completedAt":"2026-04-29T18:04:54Z","conclusion":"skipped","databaseId":73637506708,"name":"docker-manifest","startedAt":"2026-04-29T18:04:54Z","status":"completed","steps":[],"url":"https://github.com/link-foundation/box/actions/runs/25125551441/job/73637506708"},{"completedAt":"2026-04-29T18:04:54Z","conclusion":"skipped","databaseId":73637507118,"name":"build-dind-amd64","startedAt":"2026-04-29T18:04:55Z","status":"completed","steps":[],"url":"https://github.com/link-foundation/box/actions/runs/25125551441/job/73637507118"},{"completedAt":"2026-04-29T18:04:54Z","conclusion":"skipped","databaseId":73637507465,"name":"build-dind-arm64","startedAt":"2026-04-29T18:04:55Z","status":"completed","steps":[],"url":"https://github.com/link-foundation/box/actions/runs/25125551441/job/73637507465"},{"completedAt":"2026-04-29T18:04:55Z","conclusion":"skipped","databaseId":73637507533,"name":"create-release","startedAt":"2026-04-29T18:04:55Z","status":"completed","steps":[],"url":"https://github.com/link-foundation/box/actions/runs/25125551441/job/73637507533"},{"completedAt":"2026-04-29T18:04:54Z","conclusion":"skipped","databaseId":73637507618,"name":"dind-manifest","startedAt":"2026-04-29T18:04:55Z","status":"completed","steps":[],"url":"https://github.com/link-foundation/box/actions/runs/25125551441/job/73637507618"}],"name":"Build and Release Docker Image","updatedAt":"2026-04-29T18:04:55Z","url":"https://github.com/link-foundation/box/actions/runs/25125551441","workflowName":"Build and Release Docker Image"}
